[
    {
        "id": 1,
        "title": "Scholarship for College Students",
        "body": "Apply for our scholarship program available for college students pursuing a degree in technology.",
        "category": "Scholarships",
        "labels": {
            "Scholarship Type": "Domestic",
            "Eligibility": "College Students"
        },
        "link": "https://scholarship.com/apply",
        "linkedin": "https://linkedin.com/company/scholarship",
        "deadline": "2024-09-01",
        "location": "Boston, MA",
        "email": "info@scholarship.com",
        "phone": "(345) 678-9012"
    },
    {
        "id": 2,
        "title": "International Student Scholarship",
        "body": "Scholarships for international students in any field of study.",
        "category": "Scholarships",
        "labels": {
            "Scholarship Type": "International",
            "Eligibility": "All Students"
        },
        "link": "https://internationalscholarship.com/apply",
        "linkedin": "https://linkedin.com/company/international-scholarship",
        "deadline": "2024-10-01",
        "location": "New York, NY",
        "email": "info@internationalscholarship.com",
        "phone": "(567) 890-1234"
    },
    {
        "id": 3,
        "title": "STEM Scholarship",
        "body": "Scholarships for students pursuing degrees in STEM fields.",
        "category": "Scholarships",
        "labels": {
            "Scholarship Type": "Domestic",
            "Eligibility": "STEM Students"
        },
        "link": "https://stemscholarship.com/apply",
        "linkedin": "https://linkedin.com/company/stem-scholarship",
        "deadline": "2024-08-01",
        "location": "San Francisco, CA",
        "email": "info@stemscholarship.com",
        "phone": "(789) 012-3456"
    },
    {
        "id": 4,
        "title": "Graduate Scholarship Program",
        "body": "Scholarships for graduate students in any field.",
        "category": "Scholarships",
        "labels": {
            "Scholarship Type": "Domestic",
            "Eligibility": "Graduate Students"
        },
        "link": "https://graduatescholarship.com/apply",
        "linkedin": "https://linkedin.com/company/graduate-scholarship",
        "deadline": "2024-07-01",
        "location": "Chicago, IL",
        "email": "info@graduatescholarship.com",
        "phone": "(890) 123-4567"
    },
    {
        "id": 5,
        "title": "Minority Student Scholarship",
        "body": "Scholarships for minority students in various fields of study.",
        "category": "Scholarships",
        "labels": {
            "Scholarship Type": "Domestic",
            "Eligibility": "Minority Students"
        },
        "link": "https://minorityscholarship.com/apply",
        "linkedin": "https://linkedin.com/company/minority-scholarship",
        "deadline": "2024-12-01",
        "location": "Los Angeles, CA",
        "email": "info@minorityscholarship.com",
        "phone": "(901) 234-5678"
    }
]
